setup.cfg
setup.py
ddldump/__init__.py
ddldump/constants.py
ddldump/main.py
ddldump.egg-info/PKG-INFO
ddldump.egg-info/SOURCES.txt
ddldump.egg-info/dependency_links.txt
ddldump.egg-info/entry_points.txt
ddldump.egg-info/requires.txt
ddldump.egg-info/top_level.txt