Metadata-Version: 1.1
Name: ddldump
Version: 0.5
Summary: Dump a clean version of the DDLs of your tables, so you can version them.
Home-page: https://github.com/percolate/ddldump
Author: Laurent Raufaste
Author-email: analogue@glop.org
License: GPLv3
Keywords: ddldump ddl dump sql mysql postgresql sqlalchemy mysqldump pg_dump
Platform: UNKNOWN
Classifier: Development Status :: 4 - Beta
Classifier: Environment :: Console
Classifier: Intended Audience :: End Users/Desktop
Classifier: License :: OSI Approved :: GNU General Public License v3 or later (GPLv3+)
Classifier: Natural Language :: English
Classifier: Operating System :: POSIX
Classifier: Programming Language :: Python
Classifier: Topic :: Utilities
